st_image_cropper/__init__.py
st_image_cropper/example.py
st_image_cropper/frontend/build/asset-manifest.json
st_image_cropper/frontend/build/bootstrap.min.css
st_image_cropper/frontend/build/index.html
st_image_cropper/frontend/build/static/js/main.1551e0e8.js
st_image_cropper/frontend/build/static/js/main.1551e0e8.js.LICENSE.txt
st_image_cropper/frontend/build/static/js/main.1551e0e8.js.map
st_image_cropper/frontend/build/static/js/main.79b49f2d.js
st_image_cropper/frontend/build/static/js/main.79b49f2d.js.LICENSE.txt
st_image_cropper/frontend/build/static/js/main.79b49f2d.js.map
st_image_cropper/frontend/build/static/js/main.ed0017c8.js
st_image_cropper/frontend/build/static/js/main.ed0017c8.js.LICENSE.txt
st_image_cropper/frontend/build/static/js/main.ed0017c8.js.map
st_image_cropper-0.0.9.dist-info/LICENSE
st_image_cropper-0.0.9.dist-info/METADATA
st_image_cropper-0.0.9.dist-info/WHEEL
st_image_cropper-0.0.9.dist-info/top_level.txt
st_image_cropper-0.0.9.dist-info/RECORD
